{
    "name": "Qu\u00e1n Ch\u00e8 D\u1eeba Non",
    "address": "2 Ng\u00e1ch 193/220/133 Ph\u00fa Di\u1ec5n, P. Ph\u00fa Di\u1ec5n, Qu\u1eadn B\u1eafc T\u1eeb Li\u00eam H\u00e0 N\u1ed9i",
    "category": "Caf\u00e9/Dessert",
    "scores": {
        "avg_score": null,
        "location": null,
        "price": null,
        "quality": null,
        "service": null,
        "space": null
    },
    "review_count": null,
    "opening_time": "09:00",
    "closing_time": "23:00",
    "min_price": "12.000",
    "max_price": "20.000",
    "audiences": [
        "Sinh vi\u00ean",
        "C\u1eb7p \u0111\u00f4i",
        "Nh\u00f3m h\u1ed9i"
    ],
    "cuisine": "M\u00f3n Vi\u1ec7t",
    "url": "https://www.foody.vn/ha-noi/quan-che-dua-non"
}