{
    "name": "Tiger Sugar By HongKong - Tr\u1ea7n \u0110\u1ea1i Ngh\u0129a",
    "address": "265 Tr\u1ea7n \u0110\u1ea1i Ngh\u0129a, Qu\u1eadn Hai B\u00e0 Tr\u01b0ng H\u00e0 N\u1ed9i",
    "category": "Caf\u00e9/Dessert",
    "scores": {
        "avg_score": 4.4,
        "location": null,
        "price": null,
        "service": null,
        "space": null,
        "quality": null
    },
    "review_count": 1,
    "opening_time": "07:00",
    "closing_time": "23:00",
    "min_price": "20.000",
    "max_price": "40.000",
    "audiences": [
        "C\u1eb7p \u0111\u00f4i",
        "Nh\u00f3m h\u1ed9i"
    ],
    "cuisine": "M\u00f3n \u00c1",
    "url": "https://www.foody.vn/ha-noi/tiger-sugar-tran-dai-nghia"
}