{
    "name": "Somali Cat - B\u00e1nh Ng\u1ecdt & Tr\u00e0 S\u1eefa Online - Qu\u1ef3nh Mai",
    "address": "116 Ng\u00f5 E7 Qu\u1ef3nh Mai, Qu\u1eadn Hai B\u00e0 Tr\u01b0ng H\u00e0 N\u1ed9i",
    "category": "Shop Online",
    "scores": {
        "avg_score": 6.6,
        "space": 6.8,
        "location": 6.7,
        "service": 6.5,
        "price": 6.5,
        "quality": 6.5
    },
    "review_count": 21,
    "opening_time": "08:00",
    "closing_time": "21:00",
    "min_price": "30.000",
    "max_price": "100.000",
    "audiences": [
        "C\u1eb7p \u0111\u00f4i",
        "Gia \u0111\u00ecnh",
        "Nh\u00f3m h\u1ed9i"
    ],
    "cuisine": "M\u00f3n Vi\u1ec7t",
    "url": "https://www.foody.vn/ha-noi/somali-cat-banh-ngot-tra-sua-online-quynh-mai"
}