{
    "name": "BUMTRO - B\u00fan Tr\u1ed9n Nam B\u1ed9 - \u0110\u1ea1i T\u1eeb",
    "address": "2 Ng\u00f5 184 \u0110\u1ea1i T\u1eeb, Qu\u1eadn Ho\u00e0ng Mai H\u00e0 N\u1ed9i",
    "category": "Qu\u00e1n \u0103n",
    "scores": {
        "avg_score": null,
        "location": null,
        "price": null,
        "quality": null,
        "service": null,
        "space": null
    },
    "review_count": null,
    "opening_time": "07:00",
    "closing_time": "15:30",
    "min_price": "15.000",
    "max_price": "40.000",
    "audiences": [
        "Sinh vi\u00ean",
        "Gia \u0111\u00ecnh",
        "Nh\u00f3m h\u1ed9i"
    ],
    "cuisine": "M\u00f3n Vi\u1ec7t",
    "url": "https://www.foody.vn/ha-noi/bumtro-bun-tron-nam-bo-dai-tu"
}