{
    "name": "C\u00f4 L\u00ea - Nem N\u01b0\u1edbng Nha Trang - Kh\u01b0\u01a1ng Th\u01b0\u1ee3ng",
    "address": "69 Kh\u01b0\u01a1ng Th\u01b0\u1ee3ng, Qu\u1eadn \u0110\u1ed1ng \u0110a H\u00e0 N\u1ed9i",
    "category": "Qu\u00e1n \u0103n",
    "scores": {
        "avg_score": 6.6,
        "location": 7.3,
        "service": 6.9,
        "price": 6.6,
        "quality": 6.1,
        "space": 6.1
    },
    "review_count": 7,
    "opening_time": "09:00",
    "closing_time": "22:00",
    "min_price": "15.000",
    "max_price": "50.000",
    "audiences": [
        "C\u1eb7p \u0111\u00f4i",
        "Gia \u0111\u00ecnh",
        "Nh\u00f3m h\u1ed9i"
    ],
    "cuisine": "M\u00f3n Vi\u1ec7t",
    "url": "https://www.foody.vn/ha-noi/co-le-nem-nuong-nha-trang-khuong-thuong"
}