{
    "name": "Khao Lao - Vincom Center Ph\u1ea1m Ng\u1ecdc Th\u1ea1ch",
    "address": "L5-10-11, T\u1ea7ng 5 TTTM Vincom Ph\u1ea1m Ng\u1ecdc Th\u1ea1ch, 2 Ph\u1ea1m Ng\u1ecdc Th\u1ea1ch, Qu\u1eadn \u0110\u1ed1ng \u0110a H\u00e0 N\u1ed9i",
    "category": "Nh\u00e0 h\u00e0ng",
    "scores": {
        "avg_score": 7.3,
        "service": 7.7,
        "location": 7.5,
        "space": 7.3,
        "quality": 7.2,
        "price": 6.8
    },
    "review_count": 24,
    "opening_time": "11:00",
    "closing_time": "13:30 | 18:00",
    "min_price": "10.000",
    "max_price": "79.000",
    "audiences": [
        "Sinh vi\u00ean",
        "Gia \u0111\u00ecnh",
        "Gi\u1edbi v\u0103n ph\u00f2ng"
    ],
    "cuisine": "Qu\u1ed1c t\u1ebf",
    "url": "https://www.foody.vn/ha-noi/khao-lao-vincom-center-pham-ngoc-thach"
}